spreading_dye_sampler/__init__.py
spreading_dye_sampler/dye_blot.py
spreading_dye_sampler-0.2.0.dist-info/DESCRIPTION.rst
spreading_dye_sampler-0.2.0.dist-info/METADATA
spreading_dye_sampler-0.2.0.dist-info/RECORD
spreading_dye_sampler-0.2.0.dist-info/WHEEL
spreading_dye_sampler-0.2.0.dist-info/metadata.json
spreading_dye_sampler-0.2.0.dist-info/top_level.txt
