Metadata-Version: 2.0
Name: spreading-dye-sampler
Version: 0.2.0
Summary: Python implementation of the spreading dye algorithm
Home-page: https://github.com/NLeSC/spreading_dye_sampler
Author: Lourens Veen
Author-email: l.veen@esciencecenter.nl
License: Apache License 2.0
Download-URL: https://github.com/NLeSC/spreading_dye_sampler/archive/0.2.0.tar.gz
Keywords: spreading dye,spatial sampling
Platform: UNKNOWN
Classifier: Development Status :: 3 - Alpha
Classifier: License :: OSI Approved :: Apache Software License
Classifier: Operating System :: POSIX :: Linux
Classifier: Programming Language :: Python :: 2.7
Classifier: Programming Language :: Python :: 3.5
Classifier: Programming Language :: Python :: 3.6
Requires-Python: >=>=2.7, !=3.0.*, !=3.1.*, !=3.2.*, !=3.3.*, !=3.4.*, <4
Requires-Dist: numpy
